assetcoop/__init__.py
assetcoop/bam/models/character/abbot.bam
assetcoop/bam/models/character/flying_pajama_man.bam
assetcoop/bam/models/character/hud_hand.bam
assetcoop/bam/models/character/lowpoly_human_shapes.bam
assetcoop/bam/models/character/nobody.bam
assetcoop/bam/models/character/peter_panda.bam
assetcoop/bam/models/character/plain_humanoid_base.bam
assetcoop/bam/models/character/polyimpairedperson.bam
assetcoop/bam/models/character/rebecca.bam
assetcoop/bam/models/character/sofia.bam
assetcoop/bam/models/gravitytest/cylinder.bam
assetcoop/bam/models/gravitytest/interact_plane.bam
assetcoop/bam/models/gravitytest/plane.bam
assetcoop/bam/models/gravitytest/sphere_inner.bam
assetcoop/bam/models/gravitytest/sphere_outer.bam
assetcoop/bam/models/other/flyingcar.bam
assetcoop/bam/models/other/shapes.bam
assetcoop/bam/models/other/tiles.bam
assetcoop/bam/models/other/tvlegs.bam
assetcoop/bam/models/other/tvlegs.png
assetcoop/bam/models/other/vehicle.bam
assetcoop/bam/models/props/parkbench.bam
assetcoop/bam/models/scenes/appartment.bam
assetcoop/bam/models/scenes/lelycentre.bam
assetcoop/bam/models/scenes/lona.bam
assetcoop/bam/models/scenes/volcano_island.bam
assetcoop/bam/models/scenes/chess/gameboard.bam
assetcoop/bam/models/scenes/chess/gamepieces.bam
assetcoop/bam/models/scenes/chess/scene.bam
panda3d_assetcoop-0.15.dist-info/METADATA
panda3d_assetcoop-0.15.dist-info/WHEEL
panda3d_assetcoop-0.15.dist-info/top_level.txt
panda3d_assetcoop-0.15.dist-info/RECORD
