Metadata-Version: 2.1
Name: panda3d-assetcoop
Version: 0.15
Summary: Free to use panda3d models.
Home-page: https://github.com/thecheapestpixels/panda3d-assetcoop
Author: thecheapestpixels
License: UNKNOWN
Keywords: panda3d
Platform: UNKNOWN
Requires-Dist: panda3d
